{
  "name": "Get Credential via API",
  "nodes": [
    {
      "parameters": {
        "url": "=http://localhost:5678/api/v1/credentials/{{ $json.credentialId }}",
        "authentication": "genericCredentialType",
        "genericAuthType": "httpHeaderAuth",
        "sendHeaders": true,
        "headerParameters": {
          "parameters": [
            {
              "name": "X-N8N-API-KEY",
              "value": "YOUR_N8N_API_KEY_HERE"
            }
          ]
        },
        "options": {
          "response": {
            "response": {
              "fullResponse": false,
              "responseFormat": "json"
            }
          }
        }
      },
      "id": "get-credential-api",
      "name": "Get Credential via API",
      "type": "n8n-nodes-base.httpRequest",
      "position": [3952, 9232],
      "typeVersion": 4.2,
      "continueOnFail": true,
      "alwaysOutputData": true
    }
  ]
}
